pumaplot/__init__.py
pumaplot/_modidx.py
pumaplot/core.py
pumaplot-0.0.1.dist-info/LICENSE
pumaplot-0.0.1.dist-info/METADATA
pumaplot-0.0.1.dist-info/WHEEL
pumaplot-0.0.1.dist-info/entry_points.txt
pumaplot-0.0.1.dist-info/top_level.txt
pumaplot-0.0.1.dist-info/RECORD
